get_processor_codename/__main__.py
get_processor_codename/util.py
get_processor_codename-0.0.2.dist-info/METADATA
get_processor_codename-0.0.2.dist-info/WHEEL
get_processor_codename-0.0.2.dist-info/licenses/LICENSE
get_processor_codename-0.0.2.dist-info/RECORD
